BasicTree/__init__.py
BasicTree-0.0.1.dist-info/LICENSE.py
BasicTree-0.0.1.dist-info/LICENSE.txt
BasicTree-0.0.1.dist-info/METADATA
BasicTree-0.0.1.dist-info/WHEEL
BasicTree-0.0.1.dist-info/top_level.txt
BasicTree-0.0.1.dist-info/RECORD
